init/__init__.py
xhh_cation_test-0.1.0.dist-info/METADATA
xhh_cation_test-0.1.0.dist-info/WHEEL
xhh_cation_test-0.1.0.dist-info/top_level.txt
xhh_cation_test-0.1.0.dist-info/RECORD
