Metadata-Version: 2.1
Name: xhh-cation-test
Version: 0.1.0
Summary: xhh-cation-test
Home-page: https://github.com/xiaohuohumax/xhh-cation-test
Author: xiaohuohumax
License: MIT
Keywords: config
Classifier: License :: OSI Approved :: MIT License
Classifier: Programming Language :: Python
Classifier: Programming Language :: Python :: 3.8
Classifier: Programming Language :: Python :: 3.9
Classifier: Programming Language :: Python :: 3.10
Classifier: Programming Language :: Python :: 3.11
Classifier: Programming Language :: Python :: 3.12
Classifier: Programming Language :: Python :: Implementation :: PyPy
Classifier: Topic :: Software Development :: Libraries :: Python Modules
Classifier: Topic :: Utilities
Requires-Python: >=3.8
Requires-Dist: ruamel.yaml
